riscos_toolbox/__init__.py
riscos_toolbox/_types.py
riscos_toolbox/application.py
riscos_toolbox/base.py
riscos_toolbox/events.py
riscos_toolbox/gadgets/__init__.py
riscos_toolbox/gadgets/actionbutton.py
riscos_toolbox/gadgets/adjuster.py
riscos_toolbox/gadgets/button.py
riscos_toolbox/gadgets/displayfield.py
riscos_toolbox/gadgets/draggable.py
riscos_toolbox/gadgets/numberrange.py
riscos_toolbox/gadgets/optionbutton.py
riscos_toolbox/gadgets/popup.py
riscos_toolbox/gadgets/radiobutton.py
riscos_toolbox/gadgets/scrolllist.py
riscos_toolbox/gadgets/slider.py
riscos_toolbox/gadgets/stringset.py
riscos_toolbox/gadgets/textarea.py
riscos_toolbox/gadgets/writablefield.py
riscos_toolbox/mixins/__init__.py
riscos_toolbox/mixins/data_transfer.py
riscos_toolbox/mixins/printing.py
riscos_toolbox/mixins/saveas.py
riscos_toolbox/mixins/window.py
riscos_toolbox/objects/__init__.py
riscos_toolbox/objects/colourdbox.py
riscos_toolbox/objects/colourmenu.py
riscos_toolbox/objects/dcs.py
riscos_toolbox/objects/fileinfo.py
riscos_toolbox/objects/fontdbox.py
riscos_toolbox/objects/fontmenu.py
riscos_toolbox/objects/iconbar.py
riscos_toolbox/objects/menu.py
riscos_toolbox/objects/printdbox.py
riscos_toolbox/objects/proginfo.py
riscos_toolbox/objects/quit.py
riscos_toolbox/objects/saveas.py
riscos_toolbox/objects/scale.py
riscos_toolbox/objects/window.py
riscos_toolbox/user_messages/__init__.py
riscos_toolbox/user_messages/data_transfer.py
riscos_toolbox/wimp_events/__init__.py
riscos_toolbox/wimp_events/mouse_click.py
riscos_toolbox/wimp_events/redraw_window.py
test/__init__.py
test/fakeswi.py
test/test_dispatcher.py
test/test_toolbox.py
test/components/__init__.py
test/components/test_saveas.py
test/events/__init__.py
test/events/test_redraw_window.py
riscos_toolbox-1.0.2.dist-info/LICENSE
riscos_toolbox-1.0.2.dist-info/METADATA
riscos_toolbox-1.0.2.dist-info/WHEEL
riscos_toolbox-1.0.2.dist-info/top_level.txt
riscos_toolbox-1.0.2.dist-info/RECORD
