Metadata-Version: 2.1
Name: riscos-toolbox
Version: 1.0.2
Summary: RISC OS Toolbox library
Home-page: https://github.com/c-jo/riscos-toolbox
Author: Chris Johns
Author-email: chris@lessthan3.org.uk
License: UNKNOWN
Platform: UNKNOWN
Classifier: Development Status :: 2 - Pre-Alpha
Classifier: Programming Language :: Python :: 3
Classifier: License :: OSI Approved :: MIT License
Classifier: Operating System :: RISC OS
Requires-Python: >=3
